ptac/__init__.py
ptac/accessibility.py
ptac/osm.py
ptac/population.py
ptac/settings.py
ptac/util.py
ptac/urmoacjar/UrMoAC.jar
ptac/urmoacjar/__init__.py
ptac-0.1.2a0.dist-info/LICENSE.md
ptac-0.1.2a0.dist-info/METADATA
ptac-0.1.2a0.dist-info/WHEEL
ptac-0.1.2a0.dist-info/top_level.txt
ptac-0.1.2a0.dist-info/RECORD
