Metadata-Version: 2.1
Name: ptac
Version: 0.1.2a0
Summary: UNKNOWN
Home-page: https://github.com/DLR-VF/PtAC
Author: Simon Nieland, Serra Yosmaoglu
Author-email: Simon.Nieland@dlr.de, Serra.Yosmaoglu@dlr.de
License: UNKNOWN
Platform: unix
Platform: linux
Platform: win32
Classifier: Development Status :: 3 - Alpha
Classifier: Programming Language :: Python :: 3
Classifier: Operating System :: OS Independent
Classifier: License :: OSI Approved :: Eclipse Public License 2.0 (EPL-2.0)
Requires-Python: >=3.8
License-File: LICENSE.md
